bert_sklearn/__init__.py
bert_sklearn/config.py
bert_sklearn/finetune.py
bert_sklearn/sklearn.py
bert_sklearn/utils.py
bert_sklearn/data/__init__.py
bert_sklearn/data/data.py
bert_sklearn/data/utils.py
bert_sklearn/model/__init__.py
bert_sklearn/model/model.py
bert_sklearn/model/utils.py
bert_sklearn/model/pytorch_pretrained/__init__.py
bert_sklearn/model/pytorch_pretrained/file_utils.py
bert_sklearn/model/pytorch_pretrained/modeling.py
bert_sklearn/model/pytorch_pretrained/optimization.py
bert_sklearn/model/pytorch_pretrained/tokenization.py
bert_sklearn-0.3.1.dist-info/LICENSE
bert_sklearn-0.3.1.dist-info/METADATA
bert_sklearn-0.3.1.dist-info/WHEEL
bert_sklearn-0.3.1.dist-info/top_level.txt
bert_sklearn-0.3.1.dist-info/RECORD
